Workbook
Name NAV: Inputs!$B$3
Name DV01Target: Inputs!$B$4
Name Budget: Inputs!$B$5
Name CostBp: Inputs!$B$6

Sheet Inputs
A1: Case inputs
A3: Initial NAV | B3: 100000000
A4: DV01 target per bp | B4: 50000
A5: Relative loss budget | B5: 1000000
A6: One-sided transaction cost (bp) | B6: 2
A7: Routine turnover cap | B7: 0.1
A9: Edit B6, the weight block, and the apply-cost flags. Bond prices and scenario returns are values from the Python revaluation. NAV, DV01, turnover, cost, and relative P&L are formulas.

Sheet Bonds
A1: Instrument | B1: Coupon | C1: Maturity | D1: Dirty per 100 | E1: DV01 per 100 | F1: DV01 per dollar | G1: parallel_plus_100bp | H1: parallel_minus_100bp | I1: twist_steepener | J1: twist_flattener | K1: hist_2023_03_08_to_2023_03_13 | L1: hist_2023_07_31_to_2023_10_19
A2: S06M | B2: 0.0475 | C2: 2024-01-31 | D2: 99.582157 | E2: 0.005020032 | F2: =E2/D2 | G2: -0.0050284109 | H2: 0.0050538236 | I2: 0.0025237272 | J2: -0.0050284109 | K2: 0.0019341615 | L2: -4.6249968e-05
A3: S02Y | B3: 0.045 | C3: 2025-07-31 | D3: 99.194643 | E3: 0.019221307 | F3: =E3/D3 | G3: -0.019187284 | H3: 0.01956998 | I3: 0.0097269561 | J3: -0.019177852 | K3: 0.018538026 | L3: -0.0049666905
A4: S03Y | B4: 0.0425 | C4: 2026-07-31 | D4: 99.06524 | E4: 0.028245979 | F4: =E4/D4 | G4: -0.028097277 | H4: 0.028936035 | I4: 0.0091700188 | J4: -0.023106049 | K4: 0.023539386 | L4: -0.013018042
A5: S05Y | B5: 0.04 | C5: 2028-07-31 | D5: 99.087613 | E5: 0.045466572 | F5: =E5/D5 | G5: -0.044792116 | H5: 0.047014797 | I5: -0.001598515 | J5: -0.021105043 | K5: 0.029736859 | L5: -0.033737014
A6: S07Y | B6: 0.04 | C6: 2030-07-31 | D6: 99.566682 | E6: 0.061602933 | F6: =E6/D6 | G6: -0.059848764 | H6: 0.063987683 | I6: -0.023153912 | J6: -0.0073607669 | K6: 0.033983784 | L6: -0.054400708
A7: S10Y | B7: 0.04 | C7: 2033-07-31 | D7: 99.582423 | E7: 0.083242696 | F7: =E7/D7 | G7: -0.079804705 | H7: 0.087631018 | I7: -0.069974074 | J7: 0.032608772 | K7: 0.037768659 | L7: -0.082367431
A8: S20Y | B8: 0.04 | C8: 2043-07-31 | D8: 98.181553 | E8: 0.1365616 | F8: =E8/D8 | G8: -0.12773003 | H8: 0.15195228 | I8: -0.11775914 | J8: 0.06233429 | K8: 0.039337601 | L8: -0.14430817
A9: S30Y | B9: 0.04 | C9: 2053-07-31 | D9: 97.092721 | E9: 0.17013197 | F9: =E9/D9 | G9: -0.15590618 | H9: 0.1983199 | I9: -0.14582347 | J9: 0.082683534 | K9: 0.037647233 | L9: -0.15668791

Sheet Weights
A1: Instrument | B1: Current | C1: Benchmark | D1: Candidate 10% | E1: Expanded S05Y | F1: Control 2y/20y
A2: S06M | B2: 0.73582363 | C2: 0 | D2: 0.65982345 | E2: 0.39720995 | F2: 0
A3: S02Y | B3: 0 | C3: 0.1506479 | D3: 0 | E3: 0 | F3: 0.74420071
A4: S03Y | B4: 0 | C4: 0.15 | D4: 0 | E4: 0 | F4: 0
A5: S05Y | B5: 0 | C5: 0.3 | D5: 0.1 | E5: 0.44554323 | F5: 0
A6: S07Y | B6: 0 | C6: 0.2 | D6: 0 | E6: 0 | F6: 0
A7: S10Y | B7: 0 | C7: 0.1993521 | D7: 0 | E7: 0 | F7: 0
A8: S20Y | B8: 0 | C8: 0 | D8: 0 | E8: 0 | F8: 0.25579929
A9: S30Y | B9: 0.26417637 | C9: 0 | D9: 0.24017655 | E9: 0.15724682 | F9: 0
A11: Apply one-sided cost | B11: 0 | C11: 0 | D11: 1 | E11: 1 | F11: 0
A12: 1 charges buys and sells against this column. Current, benchmark, and control stay at 0.

Sheet Portfolio
A1: Item | B1: Current | C1: Benchmark | D1: Candidate 10% | E1: Expanded S05Y | F1: Control 2y/20y
A2: Apply cost | B2: =Weights!B11 | C2: =Weights!C11 | D2: =Weights!D11 | E2: =Weights!E11 | F2: =Weights!F11
A4: Market value
A5: =Weights!A2 | B5: =Weights!B2*NAV | C5: =Weights!C2*NAV | D5: =Weights!D2*NAV | E5: =Weights!E2*NAV | F5: =Weights!F2*NAV
A6: =Weights!A3 | B6: =Weights!B3*NAV | C6: =Weights!C3*NAV | D6: =Weights!D3*NAV | E6: =Weights!E3*NAV | F6: =Weights!F3*NAV
A7: =Weights!A4 | B7: =Weights!B4*NAV | C7: =Weights!C4*NAV | D7: =Weights!D4*NAV | E7: =Weights!E4*NAV | F7: =Weights!F4*NAV
A8: =Weights!A5 | B8: =Weights!B5*NAV | C8: =Weights!C5*NAV | D8: =Weights!D5*NAV | E8: =Weights!E5*NAV | F8: =Weights!F5*NAV
A9: =Weights!A6 | B9: =Weights!B6*NAV | C9: =Weights!C6*NAV | D9: =Weights!D6*NAV | E9: =Weights!E6*NAV | F9: =Weights!F6*NAV
A10: =Weights!A7 | B10: =Weights!B7*NAV | C10: =Weights!C7*NAV | D10: =Weights!D7*NAV | E10: =Weights!E7*NAV | F10: =Weights!F7*NAV
A11: =Weights!A8 | B11: =Weights!B8*NAV | C11: =Weights!C8*NAV | D11: =Weights!D8*NAV | E11: =Weights!E8*NAV | F11: =Weights!F8*NAV
A12: =Weights!A9 | B12: =Weights!B9*NAV | C12: =Weights!C9*NAV | D12: =Weights!D9*NAV | E12: =Weights!E9*NAV | F12: =Weights!F9*NAV
A13: Total market value | B13: =SUM(B5:B12) | C13: =SUM(C5:C12) | D13: =SUM(D5:D12) | E13: =SUM(E5:E12) | F13: =SUM(F5:F12)
A14: Sum of weights | B14: =SUM(Weights!B2:B9) | C14: =SUM(Weights!C2:C9) | D14: =SUM(Weights!D2:D9) | E14: =SUM(Weights!E2:E9) | F14: =SUM(Weights!F2:F9)
A15: Parallel DV01 | B15: =SUMPRODUCT(B5:B12,Bonds!$F$2:$F$9) | C15: =SUMPRODUCT(C5:C12,Bonds!$F$2:$F$9) | D15: =SUMPRODUCT(D5:D12,Bonds!$F$2:$F$9) | E15: =SUMPRODUCT(E5:E12,Bonds!$F$2:$F$9) | F15: =SUMPRODUCT(F5:F12,Bonds!$F$2:$F$9)
A16: DV01 minus target | B16: =B15-DV01Target | C16: =C15-DV01Target | D16: =D15-DV01Target | E16: =E15-DV01Target | F16: =F15-DV01Target
A17: DV01 inside ±2% | B17: =IF(ABS(B15/DV01Target-1)<=0.02,"inside","outside") | C17: =IF(ABS(C15/DV01Target-1)<=0.02,"inside","outside") | D17: =IF(ABS(D15/DV01Target-1)<=0.02,"inside","outside") | E17: =IF(ABS(E15/DV01Target-1)<=0.02,"inside","outside") | F17: =IF(ABS(F15/DV01Target-1)<=0.02,"inside","outside")
A19: Gross traded vs current (buys+sells) | B19: =SUMPRODUCT(ABS(B5:B12-$B$5:$B$12)) | C19: =SUMPRODUCT(ABS(C5:C12-$B$5:$B$12)) | D19: =SUMPRODUCT(ABS(D5:D12-$B$5:$B$12)) | E19: =SUMPRODUCT(ABS(E5:E12-$B$5:$B$12)) | F19: =SUMPRODUCT(ABS(F5:F12-$B$5:$B$12))
A20: Buys vs current | B20: =SUMPRODUCT((B5:B12-$B$5:$B$12>0)*(B5:B12-$B$5:$B$12)) | C20: =SUMPRODUCT((C5:C12-$B$5:$B$12>0)*(C5:C12-$B$5:$B$12)) | D20: =SUMPRODUCT((D5:D12-$B$5:$B$12>0)*(D5:D12-$B$5:$B$12)) | E20: =SUMPRODUCT((E5:E12-$B$5:$B$12>0)*(E5:E12-$B$5:$B$12)) | F20: =SUMPRODUCT((F5:F12-$B$5:$B$12>0)*(F5:F12-$B$5:$B$12))
A21: Sells vs current | B21: =B19-B20 | C21: =C19-C20 | D21: =D19-D20 | E21: =E19-E20 | F21: =F19-F20
A22: Turnover vs current | B22: =0.5*B19/NAV | C22: =0.5*C19/NAV | D22: =0.5*D19/NAV | E22: =0.5*E19/NAV | F22: =0.5*F19/NAV
A23: Transaction cost | B23: =B2*(CostBp/10000)*B19 | C23: =C2*(CostBp/10000)*C19 | D23: =D2*(CostBp/10000)*D19 | E23: =E2*(CostBp/10000)*E19 | F23: =F2*(CostBp/10000)*F19
A25: Scenario full-revaluation P&L, relative P&L after cost, and budget status
A26: parallel_plus_100bp P&L after cost | B26: =SUMPRODUCT(B5:B12,Bonds!$G$2:$G$9)-B23 | C26: =SUMPRODUCT(C5:C12,Bonds!$G$2:$G$9)-C23 | D26: =SUMPRODUCT(D5:D12,Bonds!$G$2:$G$9)-D23 | E26: =SUMPRODUCT(E5:E12,Bonds!$G$2:$G$9)-E23 | F26: =SUMPRODUCT(F5:F12,Bonds!$G$2:$G$9)-F23
A27: parallel_plus_100bp relative to benchmark | B27: =B26-C26 | C27: =C26-C26 | D27: =D26-C26 | E27: =E26-C26 | F27: =F26-C26
A28: parallel_plus_100bp budget | B28: =IF(B27>=-Budget,"inside","outside") | C28: =IF(C27>=-Budget,"inside","outside") | D28: =IF(D27>=-Budget,"inside","outside") | E28: =IF(E27>=-Budget,"inside","outside") | F28: =IF(F27>=-Budget,"inside","outside")
A29: parallel_minus_100bp P&L after cost | B29: =SUMPRODUCT(B5:B12,Bonds!$H$2:$H$9)-B23 | C29: =SUMPRODUCT(C5:C12,Bonds!$H$2:$H$9)-C23 | D29: =SUMPRODUCT(D5:D12,Bonds!$H$2:$H$9)-D23 | E29: =SUMPRODUCT(E5:E12,Bonds!$H$2:$H$9)-E23 | F29: =SUMPRODUCT(F5:F12,Bonds!$H$2:$H$9)-F23
A30: parallel_minus_100bp relative to benchmark | B30: =B29-C29 | C30: =C29-C29 | D30: =D29-C29 | E30: =E29-C29 | F30: =F29-C29
A31: parallel_minus_100bp budget | B31: =IF(B30>=-Budget,"inside","outside") | C31: =IF(C30>=-Budget,"inside","outside") | D31: =IF(D30>=-Budget,"inside","outside") | E31: =IF(E30>=-Budget,"inside","outside") | F31: =IF(F30>=-Budget,"inside","outside")
A32: twist_steepener P&L after cost | B32: =SUMPRODUCT(B5:B12,Bonds!$I$2:$I$9)-B23 | C32: =SUMPRODUCT(C5:C12,Bonds!$I$2:$I$9)-C23 | D32: =SUMPRODUCT(D5:D12,Bonds!$I$2:$I$9)-D23 | E32: =SUMPRODUCT(E5:E12,Bonds!$I$2:$I$9)-E23 | F32: =SUMPRODUCT(F5:F12,Bonds!$I$2:$I$9)-F23
A33: twist_steepener relative to benchmark | B33: =B32-C32 | C33: =C32-C32 | D33: =D32-C32 | E33: =E32-C32 | F33: =F32-C32
A34: twist_steepener budget | B34: =IF(B33>=-Budget,"inside","outside") | C34: =IF(C33>=-Budget,"inside","outside") | D34: =IF(D33>=-Budget,"inside","outside") | E34: =IF(E33>=-Budget,"inside","outside") | F34: =IF(F33>=-Budget,"inside","outside")
A35: twist_flattener P&L after cost | B35: =SUMPRODUCT(B5:B12,Bonds!$J$2:$J$9)-B23 | C35: =SUMPRODUCT(C5:C12,Bonds!$J$2:$J$9)-C23 | D35: =SUMPRODUCT(D5:D12,Bonds!$J$2:$J$9)-D23 | E35: =SUMPRODUCT(E5:E12,Bonds!$J$2:$J$9)-E23 | F35: =SUMPRODUCT(F5:F12,Bonds!$J$2:$J$9)-F23
A36: twist_flattener relative to benchmark | B36: =B35-C35 | C36: =C35-C35 | D36: =D35-C35 | E36: =E35-C35 | F36: =F35-C35
A37: twist_flattener budget | B37: =IF(B36>=-Budget,"inside","outside") | C37: =IF(C36>=-Budget,"inside","outside") | D37: =IF(D36>=-Budget,"inside","outside") | E37: =IF(E36>=-Budget,"inside","outside") | F37: =IF(F36>=-Budget,"inside","outside")
A38: hist_2023_03_08_to_2023_03_13 P&L after cost | B38: =SUMPRODUCT(B5:B12,Bonds!$K$2:$K$9)-B23 | C38: =SUMPRODUCT(C5:C12,Bonds!$K$2:$K$9)-C23 | D38: =SUMPRODUCT(D5:D12,Bonds!$K$2:$K$9)-D23 | E38: =SUMPRODUCT(E5:E12,Bonds!$K$2:$K$9)-E23 | F38: =SUMPRODUCT(F5:F12,Bonds!$K$2:$K$9)-F23
A39: hist_2023_03_08_to_2023_03_13 relative to benchmark | B39: =B38-C38 | C39: =C38-C38 | D39: =D38-C38 | E39: =E38-C38 | F39: =F38-C38
A40: hist_2023_03_08_to_2023_03_13 budget | B40: =IF(B39>=-Budget,"inside","outside") | C40: =IF(C39>=-Budget,"inside","outside") | D40: =IF(D39>=-Budget,"inside","outside") | E40: =IF(E39>=-Budget,"inside","outside") | F40: =IF(F39>=-Budget,"inside","outside")
A41: hist_2023_07_31_to_2023_10_19 P&L after cost | B41: =SUMPRODUCT(B5:B12,Bonds!$L$2:$L$9)-B23 | C41: =SUMPRODUCT(C5:C12,Bonds!$L$2:$L$9)-C23 | D41: =SUMPRODUCT(D5:D12,Bonds!$L$2:$L$9)-D23 | E41: =SUMPRODUCT(E5:E12,Bonds!$L$2:$L$9)-E23 | F41: =SUMPRODUCT(F5:F12,Bonds!$L$2:$L$9)-F23
A42: hist_2023_07_31_to_2023_10_19 relative to benchmark | B42: =B41-C41 | C42: =C41-C41 | D42: =D41-C41 | E42: =E41-C41 | F42: =F41-C41
A43: hist_2023_07_31_to_2023_10_19 budget | B43: =IF(B42>=-Budget,"inside","outside") | C43: =IF(C42>=-Budget,"inside","outside") | D43: =IF(D42>=-Budget,"inside","outside") | E43: =IF(E42>=-Budget,"inside","outside") | F43: =IF(F42>=-Budget,"inside","outside")

Sheet FiveYearCashFlows
A1: S05Y cash-flow discount check
A2: Present value uses Excel EXP on the continuous zero. T and the zero are values from the valuation-date curve. Sum of PV should match the S05Y dirty price on Bonds.
A4: Pay date | B4: T (ACT/365F) | C4: Cash flow per 100 | D4: Continuous zero (decimal) | E4: Discount factor | F4: Present value
A5: 2024-01-31 | B5: 0.50410959 | C5: 2 | D5: 0.054868118 | E5: =EXP(-D5*B5) | F5: =C5*E5
A6: 2024-07-31 | B6: 1.0027397 | C6: 2 | D6: 0.052739499 | E6: =EXP(-D6*B6) | F6: =C6*E6
A7: 2025-01-31 | B7: 1.5068493 | C7: 2 | D7: 0.050532189 | E7: =EXP(-D7*B7) | F7: =C7*E7
A8: 2025-07-31 | B8: 2.0027397 | C8: 2 | D8: 0.048491314 | E8: =EXP(-D8*B8) | F8: =C8*E8
A9: 2026-01-31 | B9: 2.5068493 | C9: 2 | D9: 0.046643529 | E9: =EXP(-D9*B9) | F9: =C9*E9
A10: 2026-07-31 | B10: 3.0027397 | C10: 2 | D10: 0.045084392 | E10: =EXP(-D10*B10) | F10: =C10*E10
A11: 2027-01-31 | B11: 3.5068493 | C11: 2 | D11: 0.043763779 | E11: =EXP(-D11*B11) | F11: =C11*E11
A12: 2027-07-31 | B12: 4.0027397 | C12: 2 | D12: 0.042707516 | E12: =EXP(-D12*B12) | F12: =C12*E12
A13: 2028-01-31 | B13: 4.5068493 | C13: 2 | D13: 0.04185359 | E13: =EXP(-D13*B13) | F13: =C13*E13
A14: 2028-07-31 | B14: 5.0054795 | C14: 102 | D14: 0.041196991 | E14: =EXP(-D14*B14) | F14: =C14*E14
E16: Sum of present values | F16: =SUM(F5:F14)
E17: Dirty price from Bonds (S05Y) | F17: =INDEX(Bonds!D:D,MATCH("S05Y",Bonds!A:A,0))
E18: Difference | F18: =F16-F17

Sheet Notes
A1: How to read the formulas
A3: Market value is weight times Inputs!B3. Parallel DV01 is the sum of market value times DV01 per dollar.
A4: Turnover versus the current book is 0.5 * sum of absolute market-value changes / NAV. Gross traded value is buys plus sells.
A5: Cost is the one-sided bp rate times gross traded value, and only for columns with apply-cost = 1.
A6: Scenario P&L is the sum of market value times the bond's full-revaluation return, minus that cost.
A7: Relative P&L subtracts the benchmark column. Inside the budget means relative P&L is not worse than -Budget.
A8: The steepener is -50 bp at and before 2y, +100 bp at and beyond 10y, linear in maturity between those nodes. The flattener swaps the signs. Neither is a bear steepener or a bull flattener.
A9: At the time this file was written, the expanded S05Y book's tightest scenario had a one-sided cost break-even of 4.1133 bp. The live formula below recomputes that break-even from the Portfolio sheet. A one-sided cost above it exhausts the cushion. 4.2 bp is the design note's illustration; it exhausts the cushion only if the live break-even is below 4.2.
A12: Live cushion on expanded book (tightest relative P&L + budget) | B12: =MIN(Portfolio!E27,Portfolio!E30,Portfolio!E33,Portfolio!E36,Portfolio!E39,Portfolio!E42)+Budget
A13: Live break-even one-sided cost (bp) | B13: =CostBp+B12/Portfolio!E19*10000
A14: Would 4.2 bp one-sided exhaust the expanded cushion? | B14: =IF(4.2>B13,"yes","no")
